approxposterior/__init__.py
approxposterior/approx.py
approxposterior/gmmUtils.py
approxposterior/gpUtils.py
approxposterior/likelihood.py
approxposterior/mcmcUtils.py
approxposterior/plotUtils.py
approxposterior/pool.py
approxposterior/utility.py
approxposterior/tests/__init__.py
approxposterior/tests/test_1DBayesOpt.py
approxposterior/tests/test_2DBayesOpt.py
approxposterior/tests/test_APRun.py
approxposterior/tests/test_GMM.py
approxposterior/tests/test_GPUtil.py
approxposterior/tests/test_Import.py
approxposterior/tests/test_InitGP.py
approxposterior/tests/test_KL.py
approxposterior/tests/test_MAP.py
approxposterior/tests/test_MCSE.py
approxposterior/tests/test_OptimizeGP.py
approxposterior/tests/test_TestFns.py
approxposterior/tests/test_findNewPoint.py
approxposterior/tests/test_pool.py
approxposterior-0.4.dist-info/LICENSE
approxposterior-0.4.dist-info/METADATA
approxposterior-0.4.dist-info/WHEEL
approxposterior-0.4.dist-info/top_level.txt
approxposterior-0.4.dist-info/RECORD
