Metadata-Version: 2.1
Name: approxposterior
Version: 0.4
Summary: Gaussian Process Approximation to Posterior Distributions
Home-page: https://github.com/dflemin3/approxposterior
Author: David P. Fleming
Author-email: dflemin3@uw.edu
License: MIT
Platform: UNKNOWN
Classifier: Development Status :: 5 - Production/Stable
Classifier: License :: OSI Approved :: MIT License
Classifier: Programming Language :: Python :: 3.5
Classifier: Programming Language :: Python :: 3.6
Classifier: Programming Language :: Python :: 3.7
Classifier: Topic :: Scientific/Engineering :: Astronomy
Requires-Dist: numpy
Requires-Dist: matplotlib (>=2.0.0)
Requires-Dist: scipy
Requires-Dist: george
Requires-Dist: emcee (>=3.0)
Requires-Dist: corner
Requires-Dist: sklearn
Requires-Dist: pybind11
Requires-Dist: pytest
Requires-Dist: h5py
